{
  "source": "CricHD",
  "description": "Auto-scraped cricket live stream links from CricHD",
  "updated_at": "2026-04-03T20:02:53.334294+00:00",
  "total_channels": 23,
  "online_channels": 23,
  "offline_channels": 0,
  "required_headers": {
    "User-Agent": "Mozilla/5.0 (Windows NT 10.0; Win64; x64) AppleWebKit/537.36 (KHTML, like Gecko) Chrome/131.0.0.0 Safari/537.36",
    "Referer": "https://player0003.com/"
  },
  "streams": [
    {
      "name": "Willow Cricket",
      "channel_id": "willow",
      "group": "English",
      "lang": "English",
      "logo": "",
      "m3u8_url": "https://jan.bhalocast.com:7059/hls/dowill.m3u8?md5=hPfRL0Lx_hxB61_ycj5S1Q&expires=1775251341&ch=dowill&s=758245b07b47abc86fea1b43868b2b49",
      "server": "https://jan.bhalocast.com:7059",
      "referer": "https://player0003.com/",
      "user_agent": "Mozilla/5.0 (Windows NT 10.0; Win64; x64) AppleWebKit/537.36 (KHTML, like Gecko) Chrome/131.0.0.0 Safari/537.36",
      "md5": "hPfRL0Lx_hxB61_ycj5S1Q",
      "expires": 1775251341,
      "scraped_at": "2026-04-03T20:02:22.178554+00:00",
      "status": "online"
    },
    {
      "name": "Willow HD",
      "channel_id": "willowhd",
      "group": "English",
      "lang": "English",
      "logo": "",
      "m3u8_url": "https://ting.bhalocast.com:7059/hls/hdowill.m3u8?md5=B5nvFGr8ectr3oQu-Vd7_w&expires=1775251343&ch=hdowill&s=bc4606eb439eaa3f98f2a87a51a7f0e4",
      "server": "https://ting.bhalocast.com:7059",
      "referer": "https://player0003.com/",
      "user_agent": "Mozilla/5.0 (Windows NT 10.0; Win64; x64) AppleWebKit/537.36 (KHTML, like Gecko) Chrome/131.0.0.0 Safari/537.36",
      "md5": "B5nvFGr8ectr3oQu-Vd7_w",
      "expires": 1775251343,
      "scraped_at": "2026-04-03T20:02:23.526079+00:00",
      "status": "online"
    },
    {
      "name": "Star Sports 1",
      "channel_id": "starsp",
      "group": "English",
      "lang": "English",
      "logo": "",
      "m3u8_url": "https://ting.bhalocast.com:7059/hls/star1kim.m3u8?md5=buIhHR04LXhbWuhOfF1kEw&expires=1775251344&ch=star1kim&s=fccb2c5812d278cfe73ae3a463e9036f",
      "server": "https://ting.bhalocast.com:7059",
      "referer": "https://player0003.com/",
      "user_agent": "Mozilla/5.0 (Windows NT 10.0; Win64; x64) AppleWebKit/537.36 (KHTML, like Gecko) Chrome/131.0.0.0 Safari/537.36",
      "md5": "buIhHR04LXhbWuhOfF1kEw",
      "expires": 1775251344,
      "scraped_at": "2026-04-03T20:02:25.118532+00:00",
      "status": "online"
    },
    {
      "name": "Star Sports 2",
      "channel_id": "starsp2",
      "group": "English",
      "lang": "English",
      "logo": "",
      "m3u8_url": "https://jan.bhalocast.com:7059/hls/str2cws.m3u8?md5=L88ycAj8upFtEyT5H1di7g&expires=1775251346&ch=str2cws&s=64b606b1e17ec6a0793500d5f5567a27",
      "server": "https://jan.bhalocast.com:7059",
      "referer": "https://player0003.com/",
      "user_agent": "Mozilla/5.0 (Windows NT 10.0; Win64; x64) AppleWebKit/537.36 (KHTML, like Gecko) Chrome/131.0.0.0 Safari/537.36",
      "md5": "L88ycAj8upFtEyT5H1di7g",
      "expires": 1775251346,
      "scraped_at": "2026-04-03T20:02:26.700237+00:00",
      "status": "online"
    },
    {
      "name": "Sky Sports Cricket",
      "channel_id": "crich2",
      "group": "English",
      "lang": "English",
      "logo": "",
      "m3u8_url": "https://ting.bhalocast.com:7059/hls/dodosky2.m3u8?md5=u3H8g1MJPIQsTegZudRdtg&expires=1775251347&ch=dodosky2&s=cb20416ec4b47db5052853a4cdc3ca33",
      "server": "https://ting.bhalocast.com:7059",
      "referer": "https://player0003.com/",
      "user_agent": "Mozilla/5.0 (Windows NT 10.0; Win64; x64) AppleWebKit/537.36 (KHTML, like Gecko) Chrome/131.0.0.0 Safari/537.36",
      "md5": "u3H8g1MJPIQsTegZudRdtg",
      "expires": 1775251347,
      "scraped_at": "2026-04-03T20:02:28.011502+00:00",
      "status": "online"
    },
    {
      "name": "Ten Sports",
      "channel_id": "tensp",
      "group": "English",
      "lang": "English",
      "logo": "",
      "m3u8_url": "https://dz2.bhalocast.com:7059/hls/tensp.m3u8?md5=xahjQTAlsdr8rHmAHCnRGQ&expires=1775251349&ch=tensp&s=1c1bc06ccdf9e92f0c236a48a5860c6b",
      "server": "https://dz2.bhalocast.com:7059",
      "referer": "https://player0003.com/",
      "user_agent": "Mozilla/5.0 (Windows NT 10.0; Win64; x64) AppleWebKit/537.36 (KHTML, like Gecko) Chrome/131.0.0.0 Safari/537.36",
      "md5": "xahjQTAlsdr8rHmAHCnRGQ",
      "expires": 1775251349,
      "scraped_at": "2026-04-03T20:02:29.628271+00:00",
      "status": "online"
    },
    {
      "name": "Fox Sports Cricket",
      "channel_id": "foxsports",
      "group": "English",
      "lang": "English",
      "logo": "",
      "m3u8_url": "https://jan.bhalocast.com:7059/hls/foxcric.m3u8?md5=ONEBHRRlnw55kPkh06Xi1w&expires=1775251351&ch=foxcric&s=e2ac2960dc3b195dfdd746fec107300a",
      "server": "https://jan.bhalocast.com:7059",
      "referer": "https://player0003.com/",
      "user_agent": "Mozilla/5.0 (Windows NT 10.0; Win64; x64) AppleWebKit/537.36 (KHTML, like Gecko) Chrome/131.0.0.0 Safari/537.36",
      "md5": "ONEBHRRlnw55kPkh06Xi1w",
      "expires": 1775251351,
      "scraped_at": "2026-04-03T20:02:31.230988+00:00",
      "status": "online"
    },
    {
      "name": "Star Sports Hindi",
      "channel_id": "starsp3",
      "group": "Hindi",
      "lang": "Hindi",
      "logo": "",
      "m3u8_url": "https://jan.bhalocast.com:7059/hls/str1hil.m3u8?md5=GgIFMNCPKEHGL6YssqK5tg&expires=1775251352&ch=str1hil&s=bd5fe947673dc6ebe9c56dc43918fa14",
      "server": "https://jan.bhalocast.com:7059",
      "referer": "https://player0003.com/",
      "user_agent": "Mozilla/5.0 (Windows NT 10.0; Win64; x64) AppleWebKit/537.36 (KHTML, like Gecko) Chrome/131.0.0.0 Safari/537.36",
      "md5": "GgIFMNCPKEHGL6YssqK5tg",
      "expires": 1775251352,
      "scraped_at": "2026-04-03T20:02:32.549009+00:00",
      "status": "online"
    },
    {
      "name": "Willow Xtra",
      "channel_id": "willowextra",
      "group": "Hindi",
      "lang": "Hindi",
      "logo": "",
      "m3u8_url": "https://jan.bhalocast.com:7059/hls/dwil2.m3u8?md5=boxCK065uaE8WiDVNvZlyQ&expires=1775251353&ch=dwil2&s=ace91f892243e59f9145e38f095bb5d9",
      "server": "https://jan.bhalocast.com:7059",
      "referer": "https://player0003.com/",
      "user_agent": "Mozilla/5.0 (Windows NT 10.0; Win64; x64) AppleWebKit/537.36 (KHTML, like Gecko) Chrome/131.0.0.0 Safari/537.36",
      "md5": "boxCK065uaE8WiDVNvZlyQ",
      "expires": 1775251353,
      "scraped_at": "2026-04-03T20:02:33.891480+00:00",
      "status": "online"
    },
    {
      "name": "Star Sports Tamil",
      "channel_id": "starsp1tam",
      "group": "Regional",
      "lang": "Tamil",
      "logo": "",
      "m3u8_url": "https://dz2.bhalocast.com:7059/hls/star1tamil.m3u8?md5=M_w_uAynYMtLTswvojks_A&expires=1775251355&ch=star1tamil&s=b9b2dc6054b0a0ac88888d173d14d198",
      "server": "https://dz2.bhalocast.com:7059",
      "referer": "https://player0003.com/",
      "user_agent": "Mozilla/5.0 (Windows NT 10.0; Win64; x64) AppleWebKit/537.36 (KHTML, like Gecko) Chrome/131.0.0.0 Safari/537.36",
      "md5": "M_w_uAynYMtLTswvojks_A",
      "expires": 1775251355,
      "scraped_at": "2026-04-03T20:02:35.211699+00:00",
      "status": "online"
    },
    {
      "name": "Star Sports Telugu",
      "channel_id": "starsp1telu",
      "group": "Regional",
      "lang": "Telugu",
      "logo": "",
      "m3u8_url": "https://ting.bhalocast.com:7059/hls/star1telu.m3u8?md5=2LVD0CoyyKvOGWqEEbGTQQ&expires=1775251356&ch=star1telu&s=7db45df99ba07256561c379eb2ae93fd",
      "server": "https://ting.bhalocast.com:7059",
      "referer": "https://player0003.com/",
      "user_agent": "Mozilla/5.0 (Windows NT 10.0; Win64; x64) AppleWebKit/537.36 (KHTML, like Gecko) Chrome/131.0.0.0 Safari/537.36",
      "md5": "2LVD0CoyyKvOGWqEEbGTQQ",
      "expires": 1775251356,
      "scraped_at": "2026-04-03T20:02:36.540364+00:00",
      "status": "online"
    },
    {
      "name": "PTV Sports",
      "channel_id": "ptvsp",
      "group": "Pakistan",
      "lang": "Urdu",
      "logo": "",
      "m3u8_url": "https://jan.bhalocast.com:7059/hls/ptvscpr.m3u8?md5=uaOvT1e9n5yFPGWH5dihMQ&expires=1775251357&ch=ptvscpr&s=25c09462ec2232878b02efb87b8819e0",
      "server": "https://jan.bhalocast.com:7059",
      "referer": "https://player0003.com/",
      "user_agent": "Mozilla/5.0 (Windows NT 10.0; Win64; x64) AppleWebKit/537.36 (KHTML, like Gecko) Chrome/131.0.0.0 Safari/537.36",
      "md5": "uaOvT1e9n5yFPGWH5dihMQ",
      "expires": 1775251357,
      "scraped_at": "2026-04-03T20:02:37.857227+00:00",
      "status": "online"
    },
    {
      "name": "A Sports",
      "channel_id": "asports",
      "group": "Pakistan",
      "lang": "Urdu",
      "logo": "",
      "m3u8_url": "https://ting.bhalocast.com:7059/hls/asportsd.m3u8?md5=kBiR6_2s7qRKajLfHR5rZQ&expires=1775251358&ch=asportsd&s=53b0b960b4071ffc7de0ccb60f0b2c28",
      "server": "https://ting.bhalocast.com:7059",
      "referer": "https://player0003.com/",
      "user_agent": "Mozilla/5.0 (Windows NT 10.0; Win64; x64) AppleWebKit/537.36 (KHTML, like Gecko) Chrome/131.0.0.0 Safari/537.36",
      "md5": "kBiR6_2s7qRKajLfHR5rZQ",
      "expires": 1775251358,
      "scraped_at": "2026-04-03T20:02:39.173831+00:00",
      "status": "online"
    },
    {
      "name": "Geo Super",
      "channel_id": "geosuper",
      "group": "Pakistan",
      "lang": "Urdu",
      "logo": "",
      "m3u8_url": "https://ting.bhalocast.com:7059/hls/geosp.m3u8?md5=w5Jioq2lcj2hDZzxyFRW2Q&expires=1775251360&ch=geosp&s=679991d12bbd5a7372c718784a09762f",
      "server": "https://ting.bhalocast.com:7059",
      "referer": "https://player0003.com/",
      "user_agent": "Mozilla/5.0 (Windows NT 10.0; Win64; x64) AppleWebKit/537.36 (KHTML, like Gecko) Chrome/131.0.0.0 Safari/537.36",
      "md5": "w5Jioq2lcj2hDZzxyFRW2Q",
      "expires": 1775251360,
      "scraped_at": "2026-04-03T20:02:40.477074+00:00",
      "status": "online"
    },
    {
      "name": "T Sports HD",
      "channel_id": "tsports",
      "group": "Pakistan",
      "lang": "Bengali",
      "logo": "",
      "m3u8_url": "https://dz2.bhalocast.com:7059/hls/tsportshd.m3u8?md5=KretKiX3Wdw5ulASMbokXw&expires=1775251361&ch=tsportshd&s=732e8ed99de1eeab725fb9835faff682",
      "server": "https://dz2.bhalocast.com:7059",
      "referer": "https://player0003.com/",
      "user_agent": "Mozilla/5.0 (Windows NT 10.0; Win64; x64) AppleWebKit/537.36 (KHTML, like Gecko) Chrome/131.0.0.0 Safari/537.36",
      "md5": "KretKiX3Wdw5ulASMbokXw",
      "expires": 1775251361,
      "scraped_at": "2026-04-03T20:02:41.844009+00:00",
      "status": "online"
    },
    {
      "name": "SuperSport Cricket",
      "channel_id": "supersport",
      "group": "International",
      "lang": "English",
      "logo": "",
      "m3u8_url": "https://ting.bhalocast.com:7059/hls/sscricket.m3u8?md5=kXESgUnAP2BX-C_cdngP7w&expires=1775251362&ch=sscricket&s=57fddaabe9af38954744ca771599d174",
      "server": "https://ting.bhalocast.com:7059",
      "referer": "https://player0003.com/",
      "user_agent": "Mozilla/5.0 (Windows NT 10.0; Win64; x64) AppleWebKit/537.36 (KHTML, like Gecko) Chrome/131.0.0.0 Safari/537.36",
      "md5": "kXESgUnAP2BX-C_cdngP7w",
      "expires": 1775251362,
      "scraped_at": "2026-04-03T20:02:43.192050+00:00",
      "status": "online"
    },
    {
      "name": "Astro Cricket",
      "channel_id": "astrosports",
      "group": "International",
      "lang": "English",
      "logo": "",
      "m3u8_url": "https://dz2.bhalocast.com:7059/hls/astrocric.m3u8?md5=6fwa_qHJsTj17708XHTLTQ&expires=1775251364&ch=astrocric&s=39d9484a7f2d1efdd645f507a00db1a5",
      "server": "https://dz2.bhalocast.com:7059",
      "referer": "https://player0003.com/",
      "user_agent": "Mozilla/5.0 (Windows NT 10.0; Win64; x64) AppleWebKit/537.36 (KHTML, like Gecko) Chrome/131.0.0.0 Safari/537.36",
      "md5": "6fwa_qHJsTj17708XHTLTQ",
      "expires": 1775251364,
      "scraped_at": "2026-04-03T20:02:44.497358+00:00",
      "status": "online"
    },
    {
      "name": "CricLife 1",
      "channel_id": "criclife1",
      "group": "International",
      "lang": "English",
      "logo": "",
      "m3u8_url": "https://ting.bhalocast.com:7059/hls/cl1stream.m3u8?md5=VMby_g9CGAm5Vmu0WRQENA&expires=1775251365&ch=cl1stream&s=aeb9fa7b790f906661ec7395a52ccca7",
      "server": "https://ting.bhalocast.com:7059",
      "referer": "https://player0003.com/",
      "user_agent": "Mozilla/5.0 (Windows NT 10.0; Win64; x64) AppleWebKit/537.36 (KHTML, like Gecko) Chrome/131.0.0.0 Safari/537.36",
      "md5": "VMby_g9CGAm5Vmu0WRQENA",
      "expires": 1775251365,
      "scraped_at": "2026-04-03T20:02:46.138452+00:00",
      "status": "online"
    },
    {
      "name": "CricLife 2",
      "channel_id": "criclife2",
      "group": "International",
      "lang": "English",
      "logo": "",
      "m3u8_url": "https://dz2.bhalocast.com:7059/hls/cl2stream.m3u8?md5=5lg2BVjXYy4I-R6xeB_kJQ&expires=1775251367&ch=cl2stream&s=8ac21d94e1bdb468d62cfe6f38698565",
      "server": "https://dz2.bhalocast.com:7059",
      "referer": "https://player0003.com/",
      "user_agent": "Mozilla/5.0 (Windows NT 10.0; Win64; x64) AppleWebKit/537.36 (KHTML, like Gecko) Chrome/131.0.0.0 Safari/537.36",
      "md5": "5lg2BVjXYy4I-R6xeB_kJQ",
      "expires": 1775251367,
      "scraped_at": "2026-04-03T20:02:47.481713+00:00",
      "status": "online"
    },
    {
      "name": "Sony Sports Ten 1",
      "channel_id": "sonyten1",
      "group": "International",
      "lang": "English",
      "logo": "",
      "m3u8_url": "https://ting.bhalocast.com:7059/hls/sonyten1.m3u8?md5=G4yM2GbQClEEIlstJIeEmg&expires=1775251368&ch=sonyten1&s=80b6b7d0e1c9b82aaba0c461f9938bec",
      "server": "https://ting.bhalocast.com:7059",
      "referer": "https://player0003.com/",
      "user_agent": "Mozilla/5.0 (Windows NT 10.0; Win64; x64) AppleWebKit/537.36 (KHTML, like Gecko) Chrome/131.0.0.0 Safari/537.36",
      "md5": "G4yM2GbQClEEIlstJIeEmg",
      "expires": 1775251368,
      "scraped_at": "2026-04-03T20:02:48.815462+00:00",
      "status": "online"
    },
    {
      "name": "Sony Sports Ten 2",
      "channel_id": "sonyten2",
      "group": "International",
      "lang": "English",
      "logo": "",
      "m3u8_url": "https://ting.bhalocast.com:7059/hls/sonyten2.m3u8?md5=ldtOw8lgbpVrNsjjpjMb7g&expires=1775251369&ch=sonyten2&s=d0e31060ca5bdfe2e4f15a0a0302b31f",
      "server": "https://ting.bhalocast.com:7059",
      "referer": "https://player0003.com/",
      "user_agent": "Mozilla/5.0 (Windows NT 10.0; Win64; x64) AppleWebKit/537.36 (KHTML, like Gecko) Chrome/131.0.0.0 Safari/537.36",
      "md5": "ldtOw8lgbpVrNsjjpjMb7g",
      "expires": 1775251369,
      "scraped_at": "2026-04-03T20:02:50.145395+00:00",
      "status": "online"
    },
    {
      "name": "Sony Sports Ten 5",
      "channel_id": "sonyten5",
      "group": "International",
      "lang": "English",
      "logo": "",
      "m3u8_url": "https://ting.bhalocast.com:7059/hls/sonyten5.m3u8?md5=pKrS718XpAS-KxY_k6G-dg&expires=1775251371&ch=sonyten5&s=68a51252acc78435951928992dcd861a",
      "server": "https://ting.bhalocast.com:7059",
      "referer": "https://player0003.com/",
      "user_agent": "Mozilla/5.0 (Windows NT 10.0; Win64; x64) AppleWebKit/537.36 (KHTML, like Gecko) Chrome/131.0.0.0 Safari/537.36",
      "md5": "pKrS718XpAS-KxY_k6G-dg",
      "expires": 1775251371,
      "scraped_at": "2026-04-03T20:02:51.505180+00:00",
      "status": "online"
    },
    {
      "name": "Willow 2",
      "channel_id": "willow2",
      "group": "International",
      "lang": "English",
      "logo": "",
      "m3u8_url": "https://ting.bhalocast.com:7059/hls/willow2.m3u8?md5=QOFM_4Da2SifFri6av-wBw&expires=1775251372&ch=willow2&s=fd580b6fb294225a7b617036eecf01d6",
      "server": "https://ting.bhalocast.com:7059",
      "referer": "https://player0003.com/",
      "user_agent": "Mozilla/5.0 (Windows NT 10.0; Win64; x64) AppleWebKit/537.36 (KHTML, like Gecko) Chrome/131.0.0.0 Safari/537.36",
      "md5": "QOFM_4Da2SifFri6av-wBw",
      "expires": 1775251372,
      "scraped_at": "2026-04-03T20:02:52.834107+00:00",
      "status": "online"
    }
  ]
}